pdf_watermark_remover/__init__.py
pdf_watermark_remover/remover.py
pdf_watermark_remover-0.8.0.dist-info/LICENSE
pdf_watermark_remover-0.8.0.dist-info/METADATA
pdf_watermark_remover-0.8.0.dist-info/WHEEL
pdf_watermark_remover-0.8.0.dist-info/entry_points.txt
pdf_watermark_remover-0.8.0.dist-info/top_level.txt
pdf_watermark_remover-0.8.0.dist-info/RECORD
