Metadata-Version: 2.1
Name: pdf_watermark_remover
Version: 0.8.0
Summary: A package to remove watermarks from PDF files
Home-page: https://github.com/huapohen/pdf_watermark_remover
Author: huapohen
Author-email: 694450321@qq.com
Classifier: Programming Language :: Python :: 3
Classifier: License :: OSI Approved :: Apache Software License
Classifier: Operating System :: OS Independent
Requires-Python: >=3.6
License-File: LICENSE
Requires-Dist: numpy
Requires-Dist: Pillow
Requires-Dist: PyMuPDF
Requires-Dist: reportlab
